{
    "relationships": [],
    "fields": [
        {
            "fieldId": 1,
            "fieldName": "descripcionHechos",
            "fieldType": "String",
            "fieldValidateRules": [
                "required",
                "minlength"
            ],
            "fieldValidateRulesMinlength": "3"
        },
        {
            "fieldId": 2,
            "fieldName": "estadoActualProceso",
            "fieldType": "Integer"
        },
        {
            "fieldId": 3,
            "fieldName": "fechaHechos",
            "fieldType": "LocalDate",
            "fieldValidateRules": [
                "required"
            ]
        },
        {
            "fieldId": 4,
            "fieldName": "hechos",
            "fieldType": "String",
            "fieldValidateRules": [
                "required",
                "minlength"
            ],
            "fieldValidateRulesMinlength": "3"
        }
    ],
    "changelogDate": "20151009062224",
    "dto": "mapstruct",
    "pagination": "pagination"
}